[
{
	"name": "Neuschwanstein",
	"happiness": 2,
	"culture": 4,
	"gold": 6,
	"greatPersonPoints": {"Great Merchant": 1},
	"isWonder": true,
	"uniques": [
		"[+1 Happiness, +2 Culture, +3 Gold] from every [Castle]",
		"Must have an owned [Mountain] within [2] tiles"
	],
	"requiredTech": "Dynamite",
	"quote": "'...the location is one of the most beautiful to be found, holy and unapproachable, a worthy temple for the divine friend who has brought salvation and true blessing to the world.' - King Ludwig II of Bavaria"
},
{
	"name": "Spaceship Factory",
	"production": 3,
	"requiredResource": "Aluminum",
	"cost": 360,
	"requiredBuilding": "Factory",
	"uniques": [
		"[+50]% Production when constructing [Spaceship part] units [in this city]",
		"New [Missile] units start with [15] Experience [in this city]",
		"Destroyed when the city is captured"
	],
	"requiredTech": "Robotics"
},
]
